morphvista/__init__.py
morphvista/plotter.py
morphvista-0.1.0.dist-info/METADATA
morphvista-0.1.0.dist-info/WHEEL
morphvista-0.1.0.dist-info/RECORD
