Metadata-Version: 2.4
Name: morphvista
Version: 0.1.0
Summary: A package for managing multilayer morphology data
Project-URL: Repository, https://github.com/bdpedigo/morphvista
Project-URL: Homepage, https://github.com/bdpedigo/morphvista
Project-URL: Documentation, https://bdpedigo.github.io/morphvista/
Project-URL: Issues, https://github.com/bdpedigo/morphvista/issues
Requires-Python: >=3.11
Requires-Dist: morphsync>=0.1.0
Requires-Dist: pyvista>=0.46.3
